annot/__init__.py
annot/__main__.py
annot/annot_lex.py
annot/parsetab.py
annot/visidata_plugin.py
annot/DataTables/datatables.css
annot/DataTables/datatables.js
annot/DataTables/datatables.min.css
annot/DataTables/datatables.min.js
annot/includes/default.css
annot-0.0.3.dist-info/LICENSE
annot-0.0.3.dist-info/METADATA
annot-0.0.3.dist-info/WHEEL
annot-0.0.3.dist-info/entry_points.txt
annot-0.0.3.dist-info/top_level.txt
annot-0.0.3.dist-info/RECORD
