Metadata-Version: 2.1
Name: annot
Version: 0.0.3
Summary: Annotate data analysis
Home-page: https://github.com/mclaffey/annot
Author: Mike Claffey
Author-email: mikeclaffey@yahoo.com
License: UNKNOWN
Platform: UNKNOWN
Classifier: Programming Language :: Python :: 3
Classifier: License :: OSI Approved :: MIT License
Classifier: Operating System :: OS Independent
Requires-Python: >=3.6
Requires-Dist: markdown (==3.1.1)
Requires-Dist: csvtomd
